01-RCA-Baseline/hdl/rca_alu_slice.v
module rca_alu_slice (
    input  wire       clk,
    input  wire       rst_n,
    input  wire [3:0] a, b,
    input  wire [2:0] opcode,
    input  wire       cin,      
    input  wire       scan_en,  
    input  wire       si,       
    output wire       so,       
    output reg  [3:0] result,
    output wire        cout      
);
    
    wire [4:0] full_sum;
    assign full_sum = a + b + cin;

    always @(posedge clk or negedge rst_n) begin
        if (!rst_n) begin
            result <= 4'b0;
        end else begin
            case (opcode)
                3'b000: result <= a + b + cin;
                3'b001: result <= a - b - cin;
                3'b010: result <= a & b;
                3'b011: result <= a | b;
                default: result <= 4'b0;
            endcase
        end
    end
    
    assign cout = (opcode == 3'b000) ? full_sum[4] :
                  (opcode == 3'b001) ? ((a < (b + cin))) : 1'b0;

    assign so = result[3]; 

endmodule

01-RCA-Baseline/hdl/rca_alu_top.v
module rca_alu_top (
    input  wire        clk,
    input  wire        rst_n,
    input  wire [15:0] a_16bit, b_16bit, 
    input  wire [2:0]  opcode,
    input  wire        scan_en,
    input  wire        si_top,
    output wire        so_top,
    output wire [15:0] result_16bit,
    output wire        cout_final
);

    wire c0, c1, c2; 
    wire s0, s1, s2; 

    rca_alu_slice slice0 (
        .clk(clk), .rst_n(rst_n),
        .a(a_16bit[3:0]), .b(b_16bit[3:0]),
        .opcode(opcode), .cin(1'b0),        
        .scan_en(scan_en), .si(si_top), .so(s0),
        .result(result_16bit[3:0]), .cout(c0)
    );

    rca_alu_slice slice1 (
        .clk(clk), .rst_n(rst_n),
        .a(a_16bit[7:4]), .b(b_16bit[7:4]),
        .opcode(opcode), .cin(c0),          
        .scan_en(scan_en), .si(s0), .so(s1), 
        .result(result_16bit[7:4]), .cout(c1)
    );

    rca_alu_slice slice2 (
        .clk(clk), .rst_n(rst_n),
        .a(a_16bit[11:8]), .b(b_16bit[11:8]),
        .opcode(opcode), .cin(c1),          
        .scan_en(scan_en), .si(s1), .so(s2), 
        .result(result_16bit[11:8]), .cout(c2)
    );

    rca_alu_slice slice3 (
        .clk(clk), .rst_n(rst_n),
        .a(a_16bit[15:12]), .b(b_16bit[15:12]),
        .opcode(opcode), .cin(c2),          
        .scan_en(scan_en), .si(s2), .so(so_top), 
        .result(result_16bit[15:12]), .cout(cout_final)
    );

endmodule

01-RCA-Baseline/tb/rca_alu_top_tb.v
`timescale 1ns/1ps

module rca_alu_top_tb;
    reg clk, rst_n, scan_en, si_top;
    reg [15:0] a, b;
    reg [2:0] opcode;
    wire [15:0] result;
    wire cout_final, so_top;

    rca_alu_top dut (
        .clk(clk),
        .rst_n(rst_n),
        .a_16bit(a),
        .b_16bit(b),
        .opcode(opcode),
        .scan_en(scan_en),
        .si_top(si_top),
        .so_top(so_top),
        .result_16bit(result),
        .cout_final(cout_final)
    );

    always #5 clk = ~clk;

    initial begin
        $dumpfile("rca_alu_16bit.vcd");
        $dumpvars(0, rca_alu_top_tb);

        clk = 0; rst_n = 0; scan_en = 0; si_top = 0;
        a = 0; b = 0; opcode = 0;
        #25 rst_n = 1; 

        @(negedge clk);
        a = 16'hFFFF; b = 16'h0001; opcode = 3'b000; 
        @(posedge clk);
        #20; 
        $display("EXTREME ADD: %d + %d = %d (Carry: %b)", a, b, result, cout_final);

        @(negedge clk);
        a = 16'h0000; b = 16'h0001; opcode = 3'b001; 
        @(posedge clk);
        #20;
        $display("EXTREME SUB: %d - %d = %d (Borrow: %b)", a, b, result, cout_final);

        @(negedge clk);
        a = 16'd32768; b = 16'd32768; opcode = 3'b000;
        @(posedge clk);
        #20;
        $display("MID-RANGE ADD: %d + %d = %d (Carry: %b)", a, b, result, cout_final);

        @(negedge clk);
        a = 16'hAAAA; b = 16'h5555; opcode = 3'b010;
        @(posedge clk);
        #20;
        $display("LOGIC AND: %h & %h = %h", a, b, result);

        @(negedge clk);
        a = 16'hF0F0; b = 16'h0F0F; opcode = 3'b011; 
        @(posedge clk);
        #20;
        $display("LOGIC OR: %h | %h = %h", a, b, result);

        @(negedge clk);
        scan_en = 1;
        #20;

        $display("Testing Complete. View Waves for detailed timing.");
        $finish;
    end
endmodule

01-RCA-Baseline/assets/waveforms/rca_alu_16bit.vcd
$date
	Sun May 10 18:15:39 2026
$end
$version
	Icarus Verilog
$end
$timescale
	1ps
$end
$scope module rca_alu_top_tb $end
$var wire 1 ! so_top $end
$var wire 16 " result [15:0] $end
$var wire 1 # cout_final $end
$var reg 16 $ a [15:0] $end
$var reg 16 % b [15:0] $end
$var reg 1 & clk $end
$var reg 3 ' opcode [2:0] $end
$var reg 1 ( rst_n $end
$var reg 1 ) scan_en $end
$var reg 1 * si_top $end
$scope module dut $end
$var wire 16 + a_16bit [15:0] $end
$var wire 16 , b_16bit [15:0] $end
$var wire 1 & clk $end
$var wire 3 - opcode [2:0] $end
$var wire 1 ( rst_n $end
$var wire 1 ) scan_en $end
$var wire 1 * si_top $end
$var wire 1 ! so_top $end
$var wire 1 . s2 $end
$var wire 1 / s1 $end
$var wire 1 0 s0 $end
$var wire 16 1 result_16bit [15:0] $end
$var wire 1 # cout_final $end
$var wire 1 2 c2 $end
$var wire 1 3 c1 $end
$var wire 1 4 c0 $end
$scope module slice0 $end
$var wire 4 5 a [3:0] $end
$var wire 4 6 b [3:0] $end
$var wire 1 7 cin $end
$var wire 1 & clk $end
$var wire 3 8 opcode [2:0] $end
$var wire 1 ( rst_n $end
$var wire 1 ) scan_en $end
$var wire 1 * si $end
$var wire 1 0 so $end
$var wire 5 9 full_sum [4:0] $end
$var wire 1 4 cout $end
$var reg 4 : result [3:0] $end
$upscope $end
$scope module slice1 $end
$var wire 4 ; a [3:0] $end
$var wire 4 < b [3:0] $end
$var wire 1 4 cin $end
$var wire 1 & clk $end
$var wire 3 = opcode [2:0] $end
$var wire 1 ( rst_n $end
$var wire 1 ) scan_en $end
$var wire 1 0 si $end
$var wire 1 / so $end
$var wire 5 > full_sum [4:0] $end
$var wire 1 3 cout $end
$var reg 4 ? result [3:0] $end
$upscope $end
$scope module slice2 $end
$var wire 4 @ a [3:0] $end
$var wire 4 A b [3:0] $end
$var wire 1 3 cin $end
$var wire 1 & clk $end
$var wire 3 B opcode [2:0] $end
$var wire 1 ( rst_n $end
$var wire 1 ) scan_en $end
$var wire 1 / si $end
$var wire 1 . so $end
$var wire 5 C full_sum [4:0] $end
$var wire 1 2 cout $end
$var reg 4 D result [3:0] $end
$upscope $end
$scope module slice3 $end
$var wire 4 E a [3:0] $end
$var wire 4 F b [3:0] $end
$var wire 1 2 cin $end
$var wire 1 & clk $end
$var wire 3 G opcode [2:0] $end
$var wire 1 ( rst_n $end
$var wire 1 ) scan_en $end
$var wire 1 . si $end
$var wire 1 ! so $end
$var wire 5 H full_sum [4:0] $end
$var wire 1 # cout $end
$var reg 4 I result [3:0] $end
$upscope $end
$upscope $end
$upscope $end
$enddefinitions $end
$comment Show the parameter values. $end
$dumpall
$end
#0
$dumpvars
b0 I
b0 H
b0 G
b0 F
b0 E
b0 D
b0 C
b0 B
b0 A
b0 @
b0 ?
b0 >
b0 =
b0 <
b0 ;
b0 :
b0 9
b0 8
07
b0 6
b0 5
04
03
02
b0 1
00
0/
0.
b0 -
b0 ,
b0 +
0*
0)
0(
b0 '
0&
b0 %
b0 $
0#
b0 "
0!
$end
#5000
1&
#10000
0&
#15000
1&
#20000
0&
#25000
1&
1(
#30000
1#
12
13
14
b1 6
b10000 9
b1111 5
b10000 >
b1111 ;
b10000 C
b1111 @
b10000 H
b1111 E
b1 %
b1 ,
b1111111111111111 $
b1111111111111111 +
0&
#35000
1&
#40000
0&
#45000
1&
#50000
0&
#55000
1&
#60000
b1 9
b0 5
b1 >
b0 ;
b1 C
b0 @
b1 H
b0 E
b1 '
b1 -
b1 8
b1 =
b1 B
b1 G
b0 $
b0 +
0&
#65000
1!
1.
1/
10
b1111 I
b1111 D
b1111 ?
b1111111111111111 "
b1111111111111111 1
b1111 :
1&
#70000
0&
#75000
1&
#80000
0&
#85000
1&
#90000
b0 >
04
b0 C
03
02
1#
b0 9
b0 6
b1000 F
b10000 H
b1000 E
b0 '
b0 -
b0 8
b0 =
b0 B
b0 G
b1000000000000000 %
b1000000000000000 ,
b1000000000000000 $
b1000000000000000 +
0&
#95000
00
0/
0.
0!
b0 :
b0 ?
b0 D
b0 "
b0 1
b0 I
1&
#100000
0&
#105000
1&
#110000
0&
#115000
1&
#120000
0#
b101 6
b101 <
b101 A
b101 F
b1111 9
b1010 5
b1111 >
b1010 ;
b1111 C
b1010 @
b1111 H
b1010 E
b10 '
b10 -
b10 8
b10 =
b10 B
b10 G
b101010101010101 %
b101010101010101 ,
b1010101010101010 $
b1010101010101010 +
0&
#125000
1&
#130000
0&
#135000
1&
#140000
0&
#145000
1&
#150000
b1111 6
b0 <
b1111 A
b0 F
b1111 9
b0 5
b1111 >
b1111 ;
b1111 C
b0 @
b1111 H
b1111 E
b11 '
b11 -
b11 8
b11 =
b11 B
b11 G
b111100001111 %
b111100001111 ,
b1111000011110000 $
b1111000011110000 +
0&
#155000
10
1/
1.
1!
b1111 :
b1111 ?
b1111 D
b1111111111111111 "
b1111111111111111 1
b1111 I
1&
#160000
0&
#165000
1&
#170000
0&
#175000
1&
#180000
1)
0&
